cpmsy/__init__.py
cpmsy/sy.py
cpmsy-0.1.3.dist-info/LICENSE
cpmsy-0.1.3.dist-info/METADATA
cpmsy-0.1.3.dist-info/WHEEL
cpmsy-0.1.3.dist-info/top_level.txt
cpmsy-0.1.3.dist-info/RECORD
