Metadata-Version: 2.1
Name: cpmsy
Version: 0.1.3
Summary: point cloud match
Home-page: https://pypi.org/manage/projects/cpmsy
Author: yangmiao
Author-email: 1446174581@qq.com
License: MIT
Platform: UNKNOWN
Classifier: Programming Language :: Python :: 3
Classifier: License :: OSI Approved :: MIT License
Classifier: Operating System :: OS Independent
